bondgraph/__init__.py
bondgraph/common.py
bondgraph/core.py
bondgraph/elements.py
bondgraph/junctions.py
bondgraph/visualization.py
bondgraph-0.2.0.dist-info/LICENSE
bondgraph-0.2.0.dist-info/METADATA
bondgraph-0.2.0.dist-info/WHEEL
bondgraph-0.2.0.dist-info/top_level.txt
bondgraph-0.2.0.dist-info/RECORD
