Metadata-Version: 2.1
Name: bondgraph
Version: 0.2.0
Summary: A library to create bond graphs for physical systems and generate their differential equations.
Author-email: Karl Linderhed <bondgraph@karlinde.se>
License: MIT License
Project-URL: repository, https://github.com/karlinde/bondgraph
Project-URL: Bug Tracker, https://github.com/karlinde/bondgraph/issues
Classifier: Programming Language :: Python :: 3
Classifier: License :: OSI Approved :: MIT License
Classifier: Operating System :: OS Independent
Requires-Python: >=3.10
License-File: LICENSE
Requires-Dist: sympy
Provides-Extra: visualization
Requires-Dist: graphviz ; extra == 'visualization'
